{
  "userData": {
    "bgImgSrc": "img/user-bg.jpg",
    "userAvatarSrc": "img/user-img-lg.png",
    "userName": "Dmitry Kargaev",
    "userDesc": "Freelance UX/UI designer, 80+ projects in web design, mobile apps (iOS & android) and creative projects. Open to offers."
  },
  "groupList": {
    "1": {
      "groupImg": "img/group-img-1.png",
      "groupName": "Moscow State Linguistical University"
    },
    "2": {
      "groupImg": "img/group-img-2.png",
      "groupName": "Digital freelancers group"
    },
    "3": {
      "groupImg": "img/group-img-3.png",
      "groupName": "Interaction design association"
    },
    "4": {
      "groupImg": "img/group-img-1.png",
      "groupName": "Moscow State Linguistical University"
    },
    "5": {
      "groupImg": "img/group-img-2.png",
      "groupName": "Digital freelancers group"
    },
    "6": {
      "groupImg": "img/group-img-3.png",
      "groupName": "Interaction design association"
    },
    "7": {
      "groupImg": "img/group-img-1.png",
      "groupName": "Moscow State Linguistical University"
    },
    "8": {
      "groupImg": "img/group-img-2.png",
      "groupName": "Digital freelancers group"
    },
    "9": {
      "groupImg": "img/group-img-3.png",
      "groupName": "Interaction design association"
    },
    "10": {
      "groupImg": "img/group-img-1.png",
      "groupName": "Moscow State Linguistical University"
    },
    "11": {
      "groupImg": "img/group-img-2.png",
      "groupName": "Digital freelancers group"
    },
    "12": {
      "groupImg": "img/group-img-3.png",
      "groupName": "Interaction design association"
    }
  },
  "hashtags": {
    "1": "#work",
    "2": "#business",
    "3": "#hr",
    "4": "#userinterface",
    "5": "#digital",
    "6": "#userexperience",
    "7": "#ux",
    "8": "#ui",
    "9": "#freelance"
  },
  "articles": {
    "1": {
      "artImg": "img/trend-img.jpg",
      "artName": "Moscow State Linguistical University",
      "view": "6,340"
    },
    "2": {
      "artImg": "img/trend-img-1.jpg",
      "artName": "Advices for  young HR-manage",
      "view": "8,123"
    },
    "3": {
      "artImg": "img/trend-img-2.jpg",
      "artName": "A little about  usability testing",
      "view": "3,912"
    }
  }
}
